Workbook

Sheet Sheet1
A1: Employee_ID | B1: Employee_Name | C1: Department | D1: Date_of_Joining | E1: CTC_Annual | F1: Fixed_Salary_Monthly | G1: Variable_Pay_Monthly | H1: Basic_Salary | I1: HRA | J1: Allowances | K1: PF_Deduction | L1: Professional_Tax | M1: monthly_work hours | N1: monthly_overtime hours | O1: per_hr_regular pay | P1: per_hour_overtime_pay | Q1: Overtime_Paid | R1: Net_Salary_Paid_excluding variable pay | S1: Net_Salary_Paid_including variable pay | T1: market positioning ratio | U1: market positioning index
A2: EMP001 | B2: Rahul Sharma | C2: Administration | D2: 44218 | E2: =(F2*12)+(G2*12) -> 480000 | F2: 35000 | G2: 5000 | H2: =F2*50% -> 17500 | I2: =H2*40% -> 7000 | J2: =F2-(H2+I2) -> 10500 | K2: =H2*12% -> 2100 | L2: 200 | M2: =8*26 -> 208 | N2: 5 | O2: =H2/M2 -> 84.134615 | P2: =O2*2 -> 168.26923 | Q2: =P2*N2 -> 841.34615 | R2: =(H2+I2+J2)-(K2+L2)+(Q2) -> 33541.346 | S2: =R2+G2 -> 38541.346 | T2: =S2/median_percentile!$B$1 -> 0.76473201 | U2: {=_xlfn.IFS(T2<1,"underpaid",T2>1,"overpaid",T2=1,"median pay")} -> underpaid
A3: EMP002 | B3: Priya Verma | C3: HR | D3: 43837 | E3: =(F3*12)+(G3*12) -> 600000 | F3: 45000 | G3: 5000 | H3: =F3*50% -> 22500 | I3: =H3*40% -> 9000 | J3: =F3-(H3+I3) -> 13500 | K3: =H3*12% -> 2700 | L3: 200 | M3: =8*26 -> 208 | N3: 5 | O3: =H3/M3 -> 108.17308 | P3: =O3*2 -> 216.34615 | Q3: =P3*N3 -> 1081.7308 | R3: 41800 | S3: =R3+G3 -> 46800 | T3: =S3/median_percentile!$B$1 -> 0.92859907 | U3: {=_xlfn.IFS(T3<1,"underpaid",T3>1,"overpaid",T3=1,"median pay")} -> underpaid
A4: EMP003 | B4: Amit Patel | C4: Finance | D4: 44758 | E4: =(F4*12)+(G4*12) -> 540000 | F4: 40000 | G4: 5000 | H4: =F4*50% -> 20000 | I4: =H4*40% -> 8000 | J4: =F4-(H4+I4) -> 12000 | K4: =H4*12% -> 2400 | L4: 200 | M4: =8*26 -> 208 | N4: 1 | O4: =H4/M4 -> 96.153846 | P4: =O4*2 -> 192.30769 | Q4: =P4*N4 -> 192.30769 | R4: 41200 | S4: =R4+G4 -> 46200 | T4: =S4/median_percentile!$B$1 -> 0.91669395 | U4: {=_xlfn.IFS(T4<1,"underpaid",T4>1,"overpaid",T4=1,"median pay")} -> underpaid
A5: EMP004 | B5: Sara Mcguire | C5: IT | D5: 45690 | E5: =(F5*12)+(G5*12) -> 849864 | F5: 60525 | G5: 10297 | H5: =F5*50% -> 30262.5 | I5: =H5*40% -> 12105 | J5: =F5-(H5+I5) -> 18157.5 | K5: =H5*12% -> 3631.5 | L5: 200 | M5: =8*26 -> 208 | N5: 3 | O5: =H5/M5 -> 145.49279 | P5: =O5*2 -> 290.98558 | Q5: =P5*N5 -> 872.95673 | R5: 66991 | S5: =R5+G5 -> 77288 | T5: =S5/median_percentile!$B$1 -> 1.5335377 | U5: {=_xlfn.IFS(T5<1,"underpaid",T5>1,"overpaid",T5=1,"median pay")} -> overpaid
A6: EMP005 | B6: Alisha Hebert | C6: IT | D6: 43861 | E6: =(F6*12)+(G6*12) -> 793020 | F6: 55647 | G6: 10438 | H6: =F6*50% -> 27823.5 | I6: =H6*40% -> 11129.4 | J6: =F6-(H6+I6) -> 16694.1 | K6: =H6*12% -> 3338.82 | L6: 200 | M6: =8*26 -> 208 | N6: 0 | O6: =H6/M6 -> 133.76683 | P6: =O6*2 -> 267.53365 | Q6: =P6*N6 -> 0 | R6: 62547 | S6: =R6+G6 -> 72985 | T6: =S6/median_percentile!$B$1 -> 1.4481582 | U6: {=_xlfn.IFS(T6<1,"underpaid",T6>1,"overpaid",T6=1,"median pay")} -> overpaid
A7: EMP006 | B7: Gwendolyn Sheppard | C7: Sales | D7: 44469 | E7: =(F7*12)+(G7*12) -> 521916 | F7: 38057 | G7: 5436 | H7: =F7*50% -> 19028.5 | I7: =H7*40% -> 7611.4 | J7: =F7-(H7+I7) -> 11417.1 | K7: =H7*12% -> 2283.42 | L7: 200 | M7: =8*26 -> 208 | N7: 3 | O7: =H7/M7 -> 91.483173 | P7: =O7*2 -> 182.96635 | Q7: =P7*N7 -> 548.89904 | R7: 41010 | S7: =R7+G7 -> 46446 | T7: =S7/median_percentile!$B$1 -> 0.92157505 | U7: {=_xlfn.IFS(T7<1,"underpaid",T7>1,"overpaid",T7=1,"median pay")} -> underpaid
A8: EMP007 | B8: Kristine Mccann | C8: Finance | D8: 44642 | E8: =(F8*12)+(G8*12) -> 797748 | F8: 58897 | G8: 7582 | H8: =F8*50% -> 29448.5 | I8: =H8*40% -> 11779.4 | J8: =F8-(H8+I8) -> 17669.1 | K8: =H8*12% -> 3533.82 | L8: 200 | M8: =8*26 -> 208 | N8: 0 | O8: =H8/M8 -> 141.57933 | P8: =O8*2 -> 283.15865 | Q8: =P8*N8 -> 0 | R8: 63236 | S8: =R8+G8 -> 70818 | T8: =S8/median_percentile!$B$1 -> 1.4051609 | U8: {=_xlfn.IFS(T8<1,"underpaid",T8>1,"overpaid",T8=1,"median pay")} -> overpaid
A9: EMP008 | B9: Bobby Pittman | C9: Finance | D9: 45050 | E9: =(F9*12)+(G9*12) -> 432264 | F9: 32376 | G9: 3646 | H9: =F9*50% -> 16188 | I9: =H9*40% -> 6475.2 | J9: =F9-(H9+I9) -> 9712.8 | K9: =H9*12% -> 1942.56 | L9: 200 | M9: =8*26 -> 208 | N9: 0 | O9: =H9/M9 -> 77.826923 | P9: =O9*2 -> 155.65385 | Q9: =P9*N9 -> 0 | R9: 34149 | S9: =R9+G9 -> 37795 | T9: =S9/median_percentile!$B$1 -> 0.74992311 | U9: {=_xlfn.IFS(T9<1,"underpaid",T9>1,"overpaid",T9=1,"median pay")} -> underpaid
A10: EMP009 | B10: Calvin Ramsey | C10: HR | D10: 44811 | E10: =(F10*12)+(G10*12) -> 370944 | F10: 26354 | G10: 4558 | H10: =F10*50% -> 13177 | I10: =H10*40% -> 5270.8 | J10: =F10-(H10+I10) -> 7906.2 | K10: =H10*12% -> 1581.24 | L10: 200 | M10: =8*26 -> 208 | N10: 3 | O10: =H10/M10 -> 63.350962 | P10: =O10*2 -> 126.70192 | Q10: =P10*N10 -> 380.10577 | R10: 29350 | S10: =R10+G10 -> 33908 | T10: =S10/median_percentile!$B$1 -> 0.6727978 | U10: {=_xlfn.IFS(T10<1,"underpaid",T10>1,"overpaid",T10=1,"median pay")} -> underpaid
A11: EMP010 | B11: Collin Allison | C11: IT | D11: 45610 | E11: =(F11*12)+(G11*12) -> 1056084 | F11: 76592 | G11: 11415 | H11: =F11*50% -> 38296 | I11: =H11*40% -> 15318.4 | J11: =F11-(H11+I11) -> 22977.6 | K11: =H11*12% -> 4595.52 | L11: 200 | M11: =8*26 -> 208 | N11: 2 | O11: =H11/M11 -> 184.11538 | P11: =O11*2 -> 368.23077 | Q11: =P11*N11 -> 736.46154 | R11: 84488 | S11: =R11+G11 -> 95903 | T11: =S11/median_percentile!$B$1 -> 1.9028939 | U11: {=_xlfn.IFS(T11<1,"underpaid",T11>1,"overpaid",T11=1,"median pay")} -> overpaid
A12: EMP011 | B12: Nicholas Branch | C12: IT | D12: 45637 | E12: =(F12*12)+(G12*12) -> 1047564 | F12: 78989 | G12: 8308 | H12: =F12*50% -> 39494.5 | I12: =H12*40% -> 15797.8 | J12: =F12-(H12+I12) -> 23696.7 | K12: =H12*12% -> 4739.34 | L12: 200 | M12: =8*26 -> 208 | N12: 0 | O12: =H12/M12 -> 189.8774 | P12: =O12*2 -> 379.75481 | Q12: =P12*N12 -> 0 | R12: 82358 | S12: =R12+G12 -> 90666 | T12: =S12/median_percentile!$B$1 -> 1.7989821 | U12: {=_xlfn.IFS(T12<1,"underpaid",T12>1,"overpaid",T12=1,"median pay")} -> overpaid
A13: EMP012 | B13: Emma Robinson | C13: Sales | D13: 45072 | E13: =(F13*12)+(G13*12) -> 720240 | F13: 54305 | G13: 5715 | H13: =F13*50% -> 27152.5 | I13: =H13*40% -> 10861 | J13: =F13-(H13+I13) -> 16291.5 | K13: =H13*12% -> 3258.3 | L13: 200 | M13: =8*26 -> 208 | N13: 5 | O13: =H13/M13 -> 130.54087 | P13: =O13*2 -> 261.08173 | Q13: =P13*N13 -> 1305.4087 | R13: 56562 | S13: =R13+G13 -> 62277 | T13: =S13/median_percentile!$B$1 -> 1.2356915 | U13: {=_xlfn.IFS(T13<1,"underpaid",T13>1,"overpaid",T13=1,"median pay")} -> overpaid
A14: EMP013 | B14: Pedro Cordova | C14: Sales | D14: 43684 | E14: =(F14*12)+(G14*12) -> 612780 | F14: 43856 | G14: 7209 | H14: =F14*50% -> 21928 | I14: =H14*40% -> 8771.2 | J14: =F14-(H14+I14) -> 13156.8 | K14: =H14*12% -> 2631.36 | L14: 200 | M14: =8*26 -> 208 | N14: 0 | O14: =H14/M14 -> 105.42308 | P14: =O14*2 -> 210.84615 | Q14: =P14*N14 -> 0 | R14: 48234 | S14: =R14+G14 -> 55443 | T14: =S14/median_percentile!$B$1 -> 1.1000923 | U14: {=_xlfn.IFS(T14<1,"underpaid",T14>1,"overpaid",T14=1,"median pay")} -> overpaid
... A1001: EMP1000 | B1001: shanaya gupta | C1001: IT | D1001: 43590 | E1001: =(F1001*12)+(G1001*12) -> 633600 | F1001: 46042 | G1001: 6758 | H1001: =F1001*50% -> 23021 | I1001: =H1001*40% -> 9208.4 | J1001: =F1001-(H1001+I1001) -> 13812.6 | K1001: =H1001*12% -> 2762.52 | L1001: 200 | M1001: =8*26 -> 208 | N1001: 3 | O1001: =H1001/M1001 -> 110.67788 | P1001: =O1001*2 -> 221.35577 | Q1001: =P1001*N1001 -> 664.06731 | R1001: 49838 | S1001: =R1001+G1001 -> 56596 | T1001: =S1001/median_percentile!$B$1 -> 1.1229699 | U1001: {=_xlfn.IFS(T1001<1,"underpaid",T1001>1,"overpaid",T1001=1,"median pay")} -> overpaid

Sheet median_percentile
A1: market median | B1: =MEDIAN(Sheet1!S2:S1001) -> 50398.5
A2: market 25th percentile | B2: =_xlfn.PERCENTILE.INC(Sheet1!S2:S1001,0.25) -> 41025
A3: market 75th percentile | B3: =_xlfn.PERCENTILE.INC(Sheet1!S3:S1002,0.75) -> 59889
